mls/__about__.py
mls/__init__.py
mls/cli.py
mls/manager/__init__.py
mls/manager/configure/__init__.py
mls/manager/configure/cli.py
mls/manager/configure/custom_types.py
mls/manager/configure/help.py
mls/manager/configure/utils.py
mls/manager/dts/__init__.py
mls/manager/dts/connector_cli.py
mls/manager/dts/custom_types.py
mls/manager/dts/decorators.py
mls/manager/dts/help.py
mls/manager/dts/table.py
mls/manager/dts/transfer_cli.py
mls/manager/dts/utils.py
mls/manager/job/__init__.py
mls/manager/job/cli.py
mls/manager/job/constants.py
mls/manager/job/custom_types.py
mls/manager/job/dataclasses.py
mls/manager/job/decorators.py
mls/manager/job/help.py
mls/manager/job/utils.py
mls/schema/__init__.py
mls/schema/table.py
mls/utils/__init__.py
mls/utils/cli_entrypoint_help.py
mls/utils/common.py
mls/utils/common_types.py
mls/utils/execption.py
mls/utils/fomatter.py
mls/utils/openssl.py
mls/utils/settings.py
mls/utils/style.py
mls_core/__init__.py
mls_core/client.py
mls_core/exceptions.py
mls_core/setting.py
cml_cli-0.7.3.dist-info/METADATA
cml_cli-0.7.3.dist-info/WHEEL
cml_cli-0.7.3.dist-info/entry_points.txt
cml_cli-0.7.3.dist-info/licenses/LICENSE
cml_cli-0.7.3.dist-info/RECORD
