Metadata-Version: 2.4
Name: cml-cli
Version: 0.7.3
Summary: Библиотека для работы с api Cloud.ru MLSpace
Author-email: Максим Налимов <msnalimov@cloud.ru>
License-File: LICENSE
Keywords: cloud.ru
Classifier: Operating System :: OS Independent
Classifier: Programming Language :: Python :: 3.9
Classifier: Programming Language :: Python :: 3.10
Classifier: Programming Language :: Python :: 3.11
Classifier: Programming Language :: Python :: 3.12
Requires-Python: <4,>=3.10
Requires-Dist: click==8.1.8
Requires-Dist: h11==0.16.0
Requires-Dist: keyrings-alt<6.0.0,>=5.0.2
Requires-Dist: pycryptodome<4.0.0,>=3.21.0
Requires-Dist: responses<0.26.0,>=0.25.6
Requires-Dist: tabulate<0.10.0,>=0.9.0
Requires-Dist: types-pyyaml<7.0.0.0,>=6.0.12.20241230
Requires-Dist: types-requests<3.0.0.0,>=2.32.0.20241016
Requires-Dist: types-tabulate<0.10.0.0,>=0.9.0.20241207
Provides-Extra: dev
Requires-Dist: check-manifest; extra == 'dev'
Requires-Dist: types-requests; extra == 'dev'
Provides-Extra: lint
Requires-Dist: pre-commit; extra == 'lint'
Provides-Extra: release
Requires-Dist: hatch; extra == 'release'
Requires-Dist: hatchling; extra == 'release'
Requires-Dist: python-semantic-release; extra == 'release'
Provides-Extra: test
Requires-Dist: coverage; extra == 'test'
Requires-Dist: pytest; extra == 'test'
Requires-Dist: pytest-cov; extra == 'test'
